{
    "\uc758\uc548\uba85": "\ud55c\uad6d\uc218\ucd9c\uc785\uc740\ud589\ubc95 \uc77c\ubd80\uac1c\uc815\ubc95\ub960\uc548(\ub300\uc548)",
    "vote_results": [
        {
            "type": "\ucc2c\uc131",
            "member_idxs": [
                317,
                320,
                786,
                838,
                800,
                338,
                768,
                561,
                495,
                346,
                354,
                355,
                359,
                840,
                493,
                833,
                729,
                280,
                737,
                767,
                745,
                86,
                757,
                756,
                741,
                710,
                110,
                832,
                591,
                791,
                709,
                715,
                126,
                127,
                782,
                396,
                132,
                399,
                402,
                292,
                406,
                407,
                408,
                711,
                503,
                415,
                738,
                293,
                430,
                762,
                432,
                787,
                625,
                438,
                634,
                712,
                765,
                451,
                228,
                453,
                707,
                454,
                460,
                841,
                467,
                826,
                842,
                680,
                708,
                828,
                766,
                102,
                793,
                823,
                850,
                851,
                855,
                506,
                849,
                718,
                806,
                755,
                684,
                750,
                330,
                726,
                760,
                790,
                33,
                822,
                776,
                562,
                565,
                567,
                814,
                803,
                348,
                720,
                571,
                297,
                360,
                779,
                813,
                717,
                366,
                575,
                76,
                576,
                731,
                817,
                845,
                802,
                748,
                777,
                754,
                858,
                579,
                721,
                820,
                112,
                342,
                725,
                821,
                119,
                818,
                824,
                722,
                598,
                808,
                719,
                133,
                771,
                740,
                401,
                603,
                605,
                753,
                147,
                412,
                801,
                609,
                804,
                735,
                751,
                713,
                811,
                615,
                810,
                773,
                856,
                752,
                854,
                788,
                190,
                736,
                784,
                194,
                631,
                633,
                196,
                637,
                724,
                797,
                446,
                224,
                449,
                682,
                229,
                230,
                519,
                805,
                657,
                662,
                807,
                461,
                463,
                465,
                693,
                475,
                795,
                672,
                734,
                676,
                859,
                373
            ]
        },
        {
            "type": "\uae30\uad8c",
            "member_idxs": [
                825,
                857,
                733,
                356
            ]
        },
        {
            "type": "\ubd88\ucc38",
            "member_idxs": [
                764,
                834,
                836,
                333,
                552,
                763,
                45,
                761,
                298,
                368,
                374,
                500,
                379,
                491,
                831,
                117,
                601,
                478,
                411,
                413,
                607,
                792,
                418,
                798,
                827,
                427,
                624,
                193,
                683,
                796,
                200,
                743,
                844,
                690,
                837,
                447,
                789,
                458,
                829,
                739,
                470,
                310,
                835,
                843,
                769,
                10,
                728,
                783,
                701,
                848,
                742,
                716,
                775,
                318,
                537,
                714,
                548,
                732,
                556,
                558,
                344,
                345,
                772,
                749,
                758,
                572,
                730,
                819,
                581,
                774,
                746,
                115,
                759,
                812,
                608,
                611,
                780,
                694,
                169,
                809,
                179,
                799,
                188,
                744,
                747,
                636,
                785,
                219,
                781,
                816,
                727,
                266,
                477,
                270
            ]
        },
        {
            "type": "\uccad\uac00",
            "member_idxs": [
                830,
                343,
                794,
                256
            ]
        },
        {
            "type": "\uacb0\uc11d",
            "member_idxs": [
                367,
                839,
                778,
                587,
                389,
                166,
                471,
                416,
                352,
                815,
                448,
                227,
                847
            ]
        }
    ],
    "\ud68c\ucc28": "\uc81c321\ud68c 02\ucc28",
    "\ucc98\ub9ac\ub0a0\uc9dc": "2013-12-26",
    "bill": 7900,
    "\uacb0\uacfc": "\uc6d0\uc548\uac00\uacb0"
}