{
    "\uc758\uc548\uba85": "\uce5c\ud658\uacbd\ub18d\uc5b4\uc5c5 \uc721\uc131 \ubc0f \uc720\uae30\uc2dd\ud488 \ub4f1\uc758 \uad00\ub9ac\u00b7\uc9c0\uc6d0\uc5d0 \uad00\ud55c \ubc95\ub960 \uc77c\ubd80\uac1c\uc815\ubc95\ub960\uc548(\ub300\uc548)",
    "vote_results": [
        {
            "type": "\ucc2c\uc131",
            "member_idxs": [
                320,
                786,
                838,
                836,
                800,
                552,
                763,
                768,
                561,
                495,
                45,
                343,
                761,
                355,
                359,
                840,
                367,
                839,
                280,
                737,
                767,
                745,
                757,
                491,
                756,
                587,
                741,
                710,
                110,
                832,
                791,
                715,
                396,
                399,
                402,
                292,
                406,
                407,
                408,
                607,
                503,
                792,
                415,
                738,
                418,
                798,
                827,
                427,
                432,
                787,
                794,
                438,
                193,
                683,
                634,
                200,
                712,
                690,
                825,
                765,
                789,
                451,
                228,
                453,
                454,
                458,
                829,
                841,
                467,
                842,
                739,
                256,
                310,
                843,
                708,
                769,
                766,
                10,
                783,
                848,
                742,
                850,
                851,
                506,
                849,
                775,
                806,
                755,
                714,
                548,
                750,
                726,
                790,
                33,
                822,
                732,
                556,
                562,
                803,
                772,
                720,
                571,
                758,
                779,
                717,
                730,
                366,
                575,
                731,
                817,
                845,
                802,
                819,
                748,
                774,
                860,
                721,
                725,
                818,
                722,
                808,
                719,
                133,
                412,
                356,
                801,
                608,
                804,
                611,
                780,
                735,
                713,
                773,
                799,
                856,
                752,
                188,
                815,
                190,
                736,
                724,
                797,
                446,
                785,
                219,
                230,
                519,
                805,
                461,
                463,
                465,
                816,
                795,
                672,
                734
            ]
        },
        {
            "type": "\uae30\uad8c",
            "member_idxs": [
                413
            ]
        },
        {
            "type": "\ubd88\ucc38",
            "member_idxs": [
                764,
                834,
                338,
                830,
                346,
                354,
                298,
                493,
                368,
                374,
                729,
                500,
                379,
                86,
                831,
                389,
                709,
                126,
                127,
                601,
                478,
                411,
                711,
                293,
                625,
                837,
                447,
                707,
                826,
                470,
                471,
                835,
                680,
                828,
                102,
                793,
                716,
                855,
                537,
                718,
                684,
                330,
                776,
                565,
                567,
                814,
                344,
                345,
                348,
                749,
                297,
                360,
                572,
                813,
                76,
                576,
                777,
                754,
                746,
                820,
                342,
                115,
                821,
                824,
                771,
                740,
                812,
                401,
                147,
                609,
                416,
                751,
                811,
                615,
                169,
                809,
                810,
                179,
                744,
                854,
                784,
                631,
                747,
                637,
                224,
                449,
                229,
                662,
                781,
                807,
                727,
                693,
                475,
                266,
                477,
                676,
                270,
                859,
                373
            ]
        },
        {
            "type": "\uccad\uac00",
            "member_idxs": [
                317,
                333,
                833,
                778,
                132,
                762,
                796,
                743,
                844,
                857,
                701,
                733,
                119,
                603,
                352,
                194,
                636,
                448,
                682
            ]
        },
        {
            "type": "\uacb0\uc11d",
            "member_idxs": [
                591,
                117,
                166,
                430,
                624,
                460,
                318,
                760,
                558,
                728,
                858,
                579,
                581,
                112,
                759,
                598,
                605,
                753,
                694,
                633,
                196,
                227,
                657,
                847
            ]
        }
    ],
    "\ud68c\ucc28": "\uc81c322\ud68c 10\ucc28",
    "\ucc98\ub9ac\ub0a0\uc9dc": "2014-02-28",
    "bill": 8160,
    "\uacb0\uacfc": "\uc6d0\uc548\uac00\uacb0"
}