{
    "\uc758\uc548\uba85": "\ub0a8\ubd81\uad50\ub958\ud611\ub825\uc5d0 \uad00\ud55c \ubc95\ub960 \uc77c\ubd80\uac1c\uc815\ubc95\ub960\uc548",
    "vote_results": [
        {
            "type": "\ucc2c\uc131",
            "member_idxs": [
                317,
                320,
                764,
                838,
                333,
                800,
                552,
                763,
                830,
                761,
                346,
                355,
                493,
                833,
                367,
                368,
                374,
                280,
                379,
                737,
                86,
                757,
                491,
                587,
                741,
                710,
                832,
                591,
                389,
                791,
                709,
                117,
                715,
                126,
                396,
                132,
                601,
                399,
                402,
                292,
                406,
                407,
                478,
                408,
                607,
                415,
                293,
                430,
                432,
                787,
                794,
                625,
                193,
                683,
                634,
                200,
                712,
                844,
                690,
                447,
                765,
                789,
                451,
                228,
                453,
                707,
                454,
                829,
                841,
                467,
                826,
                842,
                739,
                470,
                310,
                680,
                843,
                708,
                769,
                766,
                728,
                793,
                857,
                783,
                701,
                848,
                742,
                850,
                851,
                855,
                849,
                775,
                806,
                755,
                733,
                714,
                750,
                726,
                760,
                790,
                822,
                732,
                776,
                556,
                558,
                562,
                565,
                344,
                345,
                803,
                348,
                749,
                571,
                758,
                572,
                779,
                813,
                717,
                575,
                76,
                576,
                731,
                845,
                802,
                819,
                777,
                858,
                746,
                860,
                759,
                821,
                824,
                722,
                598,
                719,
                133,
                812,
                401,
                605,
                412,
                356,
                801,
                608,
                609,
                804,
                611,
                735,
                352,
                713,
                811,
                615,
                169,
                773,
                799,
                856,
                815,
                854,
                190,
                736,
                784,
                747,
                196,
                637,
                724,
                797,
                446,
                785,
                219,
                449,
                682,
                229,
                230,
                662,
                463,
                465,
                816,
                693,
                266,
                477,
                672,
                734,
                270,
                859
            ]
        },
        {
            "type": "\ubc18\ub300",
            "member_idxs": [
                828
            ]
        },
        {
            "type": "\uae30\uad8c",
            "member_idxs": [
                786,
                836,
                768,
                495,
                839,
                729,
                778,
                831,
                792,
                418,
                798,
                762,
                438,
                796,
                818,
                676
            ]
        },
        {
            "type": "\ubd88\ucc38",
            "member_idxs": [
                834,
                338,
                354,
                298,
                500,
                767,
                745,
                756,
                711,
                503,
                827,
                427,
                837,
                825,
                458,
                471,
                256,
                835,
                102,
                716,
                330,
                33,
                814,
                772,
                360,
                730,
                817,
                579,
                581,
                115,
                771,
                740,
                147,
                694,
                179,
                752,
                744,
                194,
                631,
                636,
                519,
                781,
                807,
                461,
                475,
                373
            ]
        },
        {
            "type": "\ucd9c\uc7a5",
            "member_idxs": [
                506,
                318,
                537,
                548,
                567,
                754,
                774,
                721,
                820,
                342,
                780,
                751,
                633,
                805,
                657,
                727
            ]
        },
        {
            "type": "\uccad\uac00",
            "member_idxs": [
                561,
                45,
                343,
                840,
                110,
                127,
                411,
                413,
                738,
                743,
                10,
                720,
                297,
                366,
                748,
                725,
                119,
                808,
                603,
                809,
                810,
                224,
                795
            ]
        },
        {
            "type": "\uacb0\uc11d",
            "member_idxs": [
                359,
                166,
                624,
                460,
                718,
                684,
                112,
                753,
                416,
                188,
                448,
                227,
                847
            ]
        }
    ],
    "\ud68c\ucc28": "\uc81c322\ud68c 08\ucc28",
    "\ucc98\ub9ac\ub0a0\uc9dc": "2014-02-20",
    "bill": 8084,
    "\uacb0\uacfc": "\uc218\uc815\uac00\uacb0"
}