{
    "\ucc98\ub9ac\ub0a0\uc9dc": "2015-08-11",
    "\uc758\uc548\uba85": "\uc784\ub300\uc8fc\ud0dd\ubc95 \uc804\ubd80\uac1c\uc815\ubc95\ub960\uc548(\ub300\uc548)",
    "bill": 9354,
    "\ud68c\ucc28": "\uc81c336\ud68c 01\ucc28",
    "vote_results": [
        {
            "type": "\ucc2c\uc131",
            "member_idxs": [
                246,
                775,
                318,
                718,
                806,
                10,
                755,
                714,
                750,
                726,
                33,
                732,
                556,
                558,
                562,
                867,
                567,
                814,
                803,
                348,
                772,
                720,
                749,
                571,
                758,
                572,
                779,
                717,
                730,
                363,
                731,
                866,
                858,
                581,
                774,
                860,
                721,
                342,
                725,
                818,
                824,
                722,
                516,
                598,
                719,
                133,
                603,
                861,
                605,
                753,
                147,
                356,
                804,
                615,
                809,
                810,
                856,
                752,
                188,
                815,
                744,
                190,
                871,
                736,
                194,
                631,
                747,
                633,
                637,
                724,
                797,
                446,
                877,
                449,
                648,
                682,
                865,
                805,
                657,
                662,
                807,
                461,
                463,
                816,
                727,
                693,
                477,
                859,
                373,
                786,
                338,
                763,
                343,
                840,
                280,
                500,
                778,
                737,
                86,
                102,
                832,
                591,
                389,
                791,
                709,
                126,
                127,
                132,
                406,
                411,
                607,
                415,
                798,
                432,
                794,
                625,
                634,
                743,
                690,
                765,
                451,
                707,
                841,
                467,
                739,
                680
            ]
        },
        {
            "type": "\ubc18\ub300",
            "member_idxs": [
                850,
                851,
                855,
                849,
                317,
                766,
                320,
                838,
                836,
                800,
                552,
                45,
                830,
                833,
                368,
                868,
                767,
                756,
                587,
                710,
                873,
                396,
                402,
                478,
                711,
                792,
                827,
                874,
                762,
                683,
                712,
                837,
                228,
                453,
                470,
                835,
                828
            ]
        },
        {
            "type": "\uae30\uad8c",
            "member_idxs": [
                768,
                561,
                359,
                839,
                729,
                741,
                831,
                793,
                715,
                601,
                292,
                413,
                738,
                427,
                293,
                787,
                193,
                825,
                789,
                454,
                829,
                826,
                842,
                310,
                784
            ]
        },
        {
            "type": "\ubd88\ucc38",
            "member_idxs": [
                801,
                230,
                733,
                548,
                822,
                344,
                575,
                845,
                748,
                777,
                754,
                863,
                115,
                876,
                401,
                608,
                609,
                611,
                780,
                751,
                352,
                169,
                773,
                799,
                785,
                448,
                227,
                475,
                764,
                834,
                761,
                298,
                493,
                367,
                374,
                745,
                757,
                491,
                399,
                857,
                418,
                430,
                200,
                447,
                458,
                460,
                471,
                256,
                843
            ]
        },
        {
            "type": "\uccad\uac00",
            "member_idxs": [
                864,
                495,
                355,
                117,
                407,
                408,
                503,
                438,
                796,
                844,
                708,
                769,
                760,
                872,
                366,
                576,
                817,
                728,
                802,
                579,
                119,
                808,
                875,
                735,
                713,
                811,
                219,
                229,
                465,
                266,
                672,
                734,
                870
            ]
        },
        {
            "type": "\uacb0\uc11d",
            "member_idxs": [
                771,
                537,
                684,
                790,
                776,
                565,
                345,
                297,
                360,
                819,
                820,
                821,
                412,
                869,
                179,
                854,
                628,
                636,
                196,
                519,
                781,
                795,
                676,
                270,
                506,
                333,
                346,
                379
            ]
        }
    ],
    "\uacb0\uacfc": "\uc6d0\uc548\uac00\uacb0"
}