{
    "\uc758\uc548\uba85": "\uae30\uc0c1\uc0b0\uc5c5\uc9c4\ud765\ubc95 \uc77c\ubd80\uac1c\uc815\ubc95\ub960\uc548(\ub300\uc548)",
    "vote_results": [
        {
            "type": "\ucc2c\uc131",
            "member_idxs": [
                766,
                801,
                775,
                318,
                537,
                718,
                806,
                10,
                684,
                733,
                548,
                750,
                726,
                790,
                33,
                732,
                776,
                556,
                558,
                562,
                867,
                803,
                348,
                720,
                749,
                571,
                360,
                572,
                779,
                813,
                717,
                576,
                731,
                817,
                845,
                802,
                819,
                748,
                866,
                774,
                860,
                721,
                342,
                725,
                821,
                818,
                824,
                598,
                808,
                719,
                133,
                771,
                401,
                603,
                861,
                753,
                147,
                412,
                356,
                869,
                608,
                609,
                804,
                611,
                780,
                352,
                713,
                811,
                615,
                169,
                809,
                799,
                856,
                752,
                744,
                190,
                871,
                736,
                194,
                636,
                637,
                797,
                446,
                785,
                219,
                449,
                648,
                227,
                865,
                229,
                519,
                805,
                657,
                461,
                463,
                816,
                727,
                693,
                475,
                795,
                870,
                676,
                850,
                506,
                320,
                786,
                764,
                838,
                800,
                552,
                338,
                763,
                495,
                45,
                355,
                359,
                298,
                840,
                833,
                367,
                368,
                839,
                280,
                500,
                778,
                868,
                379,
                737,
                767,
                86,
                756,
                741,
                710,
                832,
                591,
                389,
                709,
                793,
                873,
                396,
                132,
                399,
                857,
                402,
                407,
                478,
                711,
                607,
                792,
                415,
                418,
                798,
                874,
                293,
                787,
                794,
                625,
                193,
                683,
                712,
                743,
                844,
                690,
                451,
                453,
                707,
                454,
                829,
                841,
                467,
                826,
                842,
                739,
                256,
                310,
                680,
                828
            ]
        },
        {
            "type": "\uae30\uad8c",
            "member_idxs": [
                317,
                561,
                872,
                722,
                740,
                773,
                784
            ]
        },
        {
            "type": "\ubd88\ucc38",
            "member_idxs": [
                230,
                755,
                714,
                760,
                565,
                814,
                344,
                345,
                772,
                758,
                730,
                366,
                363,
                728,
                777,
                754,
                820,
                863,
                115,
                119,
                751,
                810,
                179,
                188,
                854,
                628,
                747,
                196,
                662,
                807,
                266,
                477,
                672,
                270,
                859,
                373,
                855,
                864,
                834,
                836,
                768,
                830,
                343,
                761,
                374,
                729,
                745,
                491,
                102,
                831,
                117,
                715,
                126,
                127,
                601,
                292,
                406,
                408,
                411,
                413,
                827,
                427,
                430,
                762,
                432,
                796,
                200,
                837,
                825,
                789,
                228,
                458,
                460,
                470,
                835,
                843
            ]
        },
        {
            "type": "\uccad\uac00",
            "member_idxs": [
                333,
                493,
                757,
                791,
                503,
                738,
                438,
                634,
                765,
                708,
                769,
                822,
                567,
                858,
                735,
                631,
                724,
                682,
                465,
                734,
                851
            ]
        },
        {
            "type": "\uacb0\uc11d",
            "member_idxs": [
                346,
                587,
                447,
                471,
                297,
                575,
                579,
                581,
                605,
                815,
                633,
                448,
                781,
                849
            ]
        }
    ],
    "\ud68c\ucc28": "\uc81c330\ud68c 04\ucc28",
    "\ucc98\ub9ac\ub0a0\uc9dc": "2015-01-12",
    "bill": 8886,
    "\uacb0\uacfc": "\uc6d0\uc548\uac00\uacb0"
}